[
    {
    "id": "MATHTYPE_FOR_XML_EDITORS_NEW_RELEASE",
    "lang": "en",
    "solutions": [
      "mtfxe"
    ],
    "products": [
      "desktop"
    ],
    "licenseStatuses": [
      "trial",
      "trial_grace_period",
      "subscription",
      "subscription_grace_period"
    ],
    "info": {
      "title": "45. Information for Oxygen XML Author users",
      "text": "If you have used previously used “MathType for Oxygen XML Author”, you need to reconfigure the External Application - Command Line  setting in Oxygen XML Author. Please follow the instructions below to use MathType for XML Editors in Oxygen XML Author."
    },
    "alertType": "info",
    "visualizations": 5,
    "priority": 75,
        "dismissible": true,
    "closable": true
  },
    {
      "id": "NOTIFICATION TEST: GIF en",
      "lang": "en",
      "products": ["addin", "addon", "desktop"],
      "solutions": ["word", "powerpoint", "docs", "slides", "mtfxe"],
      "licenseStatuses": ["trial", "trial_grace_period", "trial_expired", "subscription", "subscription_expired", "unlicensed"],
  
      "info": {
        "title": "45. NOTIFICATION TEST",
        "text": "A gif should be displayed in the notification."
      },
  
      "image": {
          "url":"https://docs.wiris.com/calcme/es/image/uuid-48dbcf09-19a7-bc10-a246-839cab6fc9cd.gif",
          "altText": "Wiris logo."
      },
      
      "alertType": "success",
      "visualizations": 35,
      "priority": 50,
      "testExpectedResult": "Notification contains a gif.",
         "dismissible": false,
      "closable": false
    },
    {
      "id": "NOTIFICATION TEST: GIF es",
      "lang": "es",
      "products": ["addin", "addon", "desktop"],
      "solutions": ["word", "powerpoint", "docs", "slides", "mtfxe"],
      "licenseStatuses": ["trial", "trial_grace_period", "trial_expired", "subscription", "subscription_expired", "unlicensed"],
    
      "info": {
        "title": "NOTIFICATION TEST",
        "text": "Un gif debería aparecer en la notificación"
      },
  
      "image": {
          "url":"https://docs.wiris.com/calcme/es/image/uuid-48dbcf09-19a7-bc10-a246-839cab6fc9cd.gif",
          "altText": "Wiris logo."
      },
      
      "alertType": "success",
      "visualizations": 35,
      "priority": 50,
  
      "testExpectedResult": "Notification contains a gif."
    },
    {
      "id": "DEFAULT_HANDWRITING_FEATURE_CHINESE",
      "lang": "zh",
      "products": [
        "addin"
      ],
      "solutions": [
        "word",
        "powerpoint"
      ],
      "licenseStatuses": [
        "trial",
        "trial_grace_period"
      ],
      "info": {
        "title": "手写公式，MathType一键转换！",
        "text": "使用手写功能，轻松输入数学公式。点击<strong><a target=\"_blank\" href=\"https://docs.wiris.com/mathtype/zh/-en--mathtype-integrations/-en--mathtype-web-interface-features/%E6%89%8B%E5%86%99%E8%BE%93%E5%85%A5.html?utm_source=fancynotification&utm_medium=mathtypems365&utm_campaign=trial&utm_content=handwritingdocumentation-addin-chinese\">此处</a></strong>，探索更多信息。"
      },
      "image": {
        "url": "https://assets.officetools.wiris.kitchen/gifs/DEFAULT_HANDWRITING_FEATURE.gif",
        "altText": "点击“前往手写模式”按钮，开始书写您的数学公式。",
        "target": "https://docs.wiris.com/mathtype/zh/-en--mathtype-integrations/-en--mathtype-web-interface-features/%E6%89%8B%E5%86%99%E8%BE%93%E5%85%A5.html?utm_source=fancynotification&utm_medium=mathtypems365&utm_campaign=trial&utm_content=handwritingdocumentation-addin-chinese"
      },
      "alertType": "info",
      "visualizations": 5,
      "priority": 1,
      "startDate": "2024/07/01"
    },
    {
      "id": "DEFAULT_HANDWRITING_FEATURE_CHINESE",
      "lang": "zh",
      "products": [
        "addon"
      ],
      "solutions": [
        "docs",
        "slides"
      ],
      "licenseStatuses": [
        "trial",
        "trial_grace_period"
      ],
      "info": {
        "title": "手写公式，MathType一键转换！",
        "text": "使用手写功能，轻松输入数学公式。点击<strong><a target=\"_blank\" href=\"https://docs.wiris.com/mathtype/zh/-en--mathtype-integrations/-en--mathtype-web-interface-features/%E6%89%8B%E5%86%99%E8%BE%93%E5%85%A5.html?utm_source=fancynotification&utm_medium=mathtypegoogle&utm_campaign=trial&utm_content=handwritingdocumentation-addon-chinese\">此处</a></strong>，探索更多信息。"
      },
      "image": {
        "url": "https://assets.officetools.wiris.kitchen/gifs/DEFAULT_HANDWRITING_FEATURE.gif",
        "altText": "点击“前往手写模式”按钮，开始书写您的数学公式。",
        "target": "https://docs.wiris.com/mathtype/zh/-en--mathtype-integrations/-en--mathtype-web-interface-features/%E6%89%8B%E5%86%99%E8%BE%93%E5%85%A5.html?utm_source=fancynotification&utm_medium=mathtypegoogle&utm_campaign=trial&utm_content=handwritingdocumentation-addon-chinese"
      },
      "alertType": "info",
      "visualizations": 5,
      "priority": 1,
      "startDate": "2024/07/01"
    },
    {
      "id": "LEARNING_LEMUR_BETA",
      "lang": "en",
      "products": [
        "addon"
      ],
      "solutions": [
        "docs",
        "slides"
      ],
      "licenseStatuses": [
        "trial",
        "trial_grace_period"
      ],
      "info": {
        "title": "Join the math revolution in Google Classroom!",
        "text": "Learning Lemur Beta is here! Create unique math quizzes for your students with our new open platform. Start creating!"
      },
      "image": {
        "url": "https://assets.officetools.wiris.kitchen/gifs/LEARNING_LEMUR_BETA.jpg",
        "altText": "Learning Lemur Beta testing.",
        "target": "https://learning-lemur.com/?utm_source=fancynotification&utm_medium=mathtypegoogle&utm_campaign=trial&utm_term=betalearninglemur&utm_content=startcreating&sf_campid=7015p000000iOM8AAM"
      },
      "alertType": "info",
      "visualizations": 3,
      "priority": 1,
      "startDate": "2024/07/01"
    },
    {
      "id": "LEARNING_LEMUR_BETA",
      "lang": "en",
      "products": [
        "addon"
      ],
      "solutions": [
        "docs",
        "slides"
      ],
      "licenseStatuses": [
        "subscription",
        "subscription_grace_period"
      ],
      "info": {
        "title": "Join the math revolution in Google Classroom!",
        "text": "Learning Lemur Beta is here! Create unique math quizzes for your students with our new open platform. Start creating!"
      },
      "image": {
        "url": "https://assets.officetools.wiris.kitchen/gifs/LEARNING_LEMUR_BETA.jpg",
        "altText": "Learning Lemur Beta testing.",
        "target": "https://learning-lemur.com/?utm_source=fancynotification&utm_medium=mathtypegoogle&utm_campaign=licensed&utm_term=betalearninglemur&utm_content=startcreating&sf_campid=7015p000000iOM8AAM"
      },
      "alertType": "info",
      "visualizations": 3,
      "priority": 1,
      "startDate": "2024/07/01"
    },
    {
      "id": "LEARNING_LEMUR_BETA",
      "lang": "es",
      "products": [
        "addon"
      ],
      "solutions": [
        "docs",
        "slides"
      ],
      "licenseStatuses": [
        "trial",
        "trial_grace_period"
      ],
      "info": {
        "title": "¡Únete a la revolución matemática en Google Classroom!",
        "text": "¡Learning Lemur Beta ya está aquí! Crea preguntas de matemáticas únicas para tus alumnos con nuestra nueva plataforma abierta. ¡Empieza a crear!"
      },
      "image": {
        "url": "https://assets.officetools.wiris.kitchen/gifs/LEARNING_LEMUR_BETA.jpg",
        "altText": "Learning Lemur Beta testing.",
        "target": "https://learning-lemur.com/?utm_source=fancynotification&utm_medium=mathtypegoogle&utm_campaign=trial&utm_term=betalearninglemur&utm_content=startcreating&sf_campid=7015p000000iOM8AAM"
      },
      "alertType": "info",
      "visualizations": 3,
      "priority": 1,
      "startDate": "2024/07/01"
    },
    {
      "id": "LEARNING_LEMUR_BETA",
      "lang": "es",
      "products": [
        "addon"
      ],
      "solutions": [
        "docs",
        "slides"
      ],
      "licenseStatuses": [
        "subscription",
        "subscription_grace_period"
      ],
      "info": {
        "title": "¡Únete a la revolución matemática en Google Classroom!",
        "text": "¡Learning Lemur Beta ya está aquí! Crea preguntas de matemáticas únicas para tus alumnos con nuestra nueva plataforma abierta. ¡Empieza a crear!"
      },
      "image": {
        "url": "https://assets.officetools.wiris.kitchen/gifs/LEARNING_LEMUR_BETA.jpg",
        "altText": "Learning Lemur Beta testing.",
        "target": "https://learning-lemur.com/?utm_source=fancynotification&utm_medium=mathtypegoogle&utm_campaign=licensed&utm_term=betalearninglemur&utm_content=startcreating&sf_campid=7015p000000iOM8AAM"
      },
      "alertType": "info",
      "visualizations": 3,
      "priority": 1,
      "startDate": "2024/07/01"
    },
    {
      "id": "EQUATION_EDITOR_PAINS_2024",
      "lang": "en",
      "products": [
        "addin"
      ],
      "solutions": [
        "word",
        "powerpoint"
      ],
      "licenseStatuses": [
        "trial",
        "trial_grace_period"
      ],
      "info": {
        "title": "Your feedback is valuable to us!",
        "text": "Please answer this <a target=\"_blank\" href=\"https://wirisscience.typeform.com/to/Y6gxiyMP\">1-minute survey</a>"
      },
      "alertType": "info",
      "visualizations": 5,
      "priority": 1,
      "startDate": "2024/05/31",
      "endData": "2024/07/01"
    },
    {
      "id": "EQUATION_EDITOR_PAINS_2024",
      "lang": "en",
      "products": [
        "addin"
      ],
      "solutions": [
        "word",
        "powerpoint"
      ],
      "licenseStatuses": [
        "subscription",
        "subscription_grace_period"
      ],
      "info": {
        "title": "Your feedback is valuable to us!",
        "text": "Please answer this <a target=\"_blank\" href=\"https://wirisscience.typeform.com/to/bIVbP9mj\">1-minute survey</a>"
      },
      "alertType": "info",
      "visualizations": 5,
      "priority": 1,
      "startDate": "2024/05/31",
      "endData": "2024/07/01"
    },
    {
      "id": "EQUATION_EDITOR_PAINS_2024",
      "lang": "zh",
      "products": [
        "addin"
      ],
      "solutions": [
        "word",
        "powerpoint"
      ],
      "licenseStatuses": [
        "trial",
        "trial_grace_period"
      ],
      "info": {
        "title": "您的反馈对我们十分宝贵！",
        "text": "请您抽出 1 分钟时间填写<a target=\"_blank\" href=\"https://wirisscience.typeform.com/to/pPXv1m66\">此份问卷调查</a>"
      },
      "alertType": "info",
      "visualizations": 5,
      "priority": 1,
      "startDate": "2024/05/31",
      "endData": "2024/07/01"
    },
    {
      "id": "EQUATION_EDITOR_PAINS_2024",
      "lang": "zh",
      "products": [
        "addin"
      ],
      "solutions": [
        "word",
        "powerpoint"
      ],
      "licenseStatuses": [
        "subscription",
        "subscription_grace_period"
      ],
      "info": {
        "title": "您的反馈对我们十分宝贵！",
        "text": "请您抽出 1 分钟时间填写<a target=\"_blank\" href=\"https://wirisscience.typeform.com/to/WjP4Yccc\">此份问卷调查</a>"
      },
      "alertType": "info",
      "visualizations": 5,
      "priority": 1,
      "startDate": "2024/05/31",
      "endData": "2024/07/01"
    },
    {
        "id": "EQUATION_EDITOR_PAINS_2024",
        "lang": "en",
        "products": [
          "addon"
        ],
        "solutions": [
          "docs",
          "slides"
        ],
        "licenseStatuses": [
          "trial",
          "trial_grace_period"
        ],
        "info": {
          "title": "Your feedback is valuable to us!",
          "text": "Please answer this <a target=\"_blank\" href=\"https://wirisscience.typeform.com/to/ieeRuhKE\">1-minute survey</a>"
        },
        "alertType": "info",
        "visualizations": 5,
        "priority": 1,
        "startDate": "2024/05/31",
        "endData": "2024/07/01"
      },
      {
        "id": "EQUATION_EDITOR_PAINS_2024",
        "lang": "en",
        "products": [
          "addon"
        ],
        "solutions": [
          "docs",
          "slides"
        ],
        "licenseStatuses": [
          "subscription",
          "subscription_grace_period"
        ],
        "info": {
          "title": "Your feedback is valuable to us!",
          "text": "Please answer this <a target=\"_blank\" href=\"https://wirisscience.typeform.com/to/FRaJe2Xp\">1-minute survey</a>"
        },
        "alertType": "info",
        "visualizations": 5,
        "priority": 1,
        "startDate": "2024/05/31",
        "endData": "2024/07/01"
      },
      {
        "id": "EQUATION_EDITOR_PAINS_2024",
        "lang": "zh",
        "products": [
          "addon"
        ],
        "solutions": [
          "docs",
          "slides"
        ],
        "licenseStatuses": [
          "trial",
          "trial_grace_period"
        ],
        "info": {
          "title": "您的反馈对我们十分宝贵！",
          "text": "请您抽出 1 分钟时间填写<a target=\"_blank\" href=\"https://wirisscience.typeform.com/to/eQvqraxw\">此份问卷调查</a>"
        },
        "alertType": "info",
        "visualizations": 5,
        "priority": 1,
        "startDate": "2024/05/31",
        "endData": "2024/07/01"
      },
      {
        "id": "EQUATION_EDITOR_PAINS_2024",
        "lang": "zh",
        "products": [
          "addon"
        ],
        "solutions": [
          "docs",
          "slides"
        ],
        "licenseStatuses": [
          "subscription",
          "subscription_grace_period"
        ],
        "info": {
          "title": "您的反馈对我们十分宝贵！",
          "text": "请您抽出 1 分钟时间填写<a target=\"_blank\" href=\"https://wirisscience.typeform.com/to/IdB6jRqe\">此份问卷调查</a>"
        },
        "alertType": "info",
        "visualizations": 5,
        "priority": 1,
        "startDate": "2024/05/31",
        "endData": "2024/07/01"
      },
      {
        "id": "EQUATION_EDITOR_PAINS_2024",
        "lang": "es",
        "products": [
          "addin"
        ],
        "solutions": [
          "word",
          "powerpoint"
        ],
        "licenseStatuses": [
          "trial",
          "trial_grace_period"
        ],
        "info": {
          "title": "Your feedback is valuable to us!",
          "text": "Please answer this <a target=\"_blank\" href=\"https://wirisscience.typeform.com/to/Y6gxiyMP\">1-minute survey</a>"
        },
        "alertType": "info",
        "visualizations": 5,
        "priority": 1,
        "startDate": "2024/05/31",
        "endData": "2024/07/01"
      },
      {
        "id": "EQUATION_EDITOR_PAINS_2024",
        "lang": "es",
        "products": [
          "addin"
        ],
        "solutions": [
          "word",
          "powerpoint"
        ],
        "licenseStatuses": [
          "subscription",
          "subscription_grace_period"
        ],
        "info": {
          "title": "Your feedback is valuable to us!",
          "text": "Please answer this <a target=\"_blank\" href=\"https://wirisscience.typeform.com/to/bIVbP9mj\">1-minute survey</a>"
        },
        "alertType": "info",
        "visualizations": 5,
        "priority": 1,
        "startDate": "2024/05/31",
        "endData": "2024/07/01"
      },
      {
        "id": "EQUATION_EDITOR_PAINS_2024",
        "lang": "es",
        "products": [
          "addon"
        ],
        "solutions": [
          "docs",
          "slides"
        ],
        "licenseStatuses": [
          "trial",
          "trial_grace_period"
        ],
        "info": {
          "title": "Your feedback is valuable to us!",
          "text": "Please answer this <a target=\"_blank\" href=\"https://wirisscience.typeform.com/to/ieeRuhKE\">1-minute survey</a>"
        },
        "alertType": "info",
        "visualizations": 5,
        "priority": 1,
        "startDate": "2024/05/31",
        "endData": "2024/07/01"
      },
      {
        "id": "EQUATION_EDITOR_PAINS_2024",
        "lang": "es",
        "products": [
          "addon"
        ],
        "solutions": [
          "docs",
          "slides"
        ],
        "licenseStatuses": [
          "subscription",
          "subscription_grace_period"
        ],
        "info": {
          "title": "Your feedback is valuable to us!",
          "text": "Please answer this <a target=\"_blank\" href=\"https://wirisscience.typeform.com/to/FRaJe2Xp\">1-minute survey</a>"
        },
        "alertType": "info",
        "visualizations": 5,
        "priority": 1,
        "startDate": "2024/05/31",
        "endData": "2024/07/01"
      }
  ]
